Metadata-Version: 1.0
Name: zoey-distributions
Version: 0.1
Summary: Gaussian distributions and Binomial distributions
Home-page: UNKNOWN
Author: Jadesola Adedokun
Author-email: jadesolaadedokun@gmail.com
License: UNKNOWN
Platform: UNKNOWN
